src/hosszub_test/__init__.py
src/hosszub_test/example.py
hosszub_test-0.0.1.dist-info/LICENSE
hosszub_test-0.0.1.dist-info/METADATA
hosszub_test-0.0.1.dist-info/WHEEL
hosszub_test-0.0.1.dist-info/entry_points.txt
hosszub_test-0.0.1.dist-info/top_level.txt
hosszub_test-0.0.1.dist-info/RECORD
