Metadata-Version: 2.1
Name: hosszub-test
Version: 0.0.1
License-File: LICENSE
Requires-Dist: requests
Requires-Dist: importlib-metadata ; python_version < "3.9"
